st_kedro_viz_component/__init__.py
st_kedro_viz_component/frontend/build/asset-manifest.json
st_kedro_viz_component/frontend/build/bootstrap.min.css
st_kedro_viz_component/frontend/build/index.html
st_kedro_viz_component/frontend/build/precache-manifest.de89d07d6c9d9a8e16007fe69ab9aae6.js
st_kedro_viz_component/frontend/build/service-worker.js
st_kedro_viz_component/frontend/build/static/css/2.1096dae2.chunk.css
st_kedro_viz_component/frontend/build/static/css/2.1096dae2.chunk.css.map
st_kedro_viz_component/frontend/build/static/js/2.91a3a690.chunk.js
st_kedro_viz_component/frontend/build/static/js/2.91a3a690.chunk.js.LICENSE.txt
st_kedro_viz_component/frontend/build/static/js/2.91a3a690.chunk.js.map
st_kedro_viz_component/frontend/build/static/js/main.af195e39.chunk.js
st_kedro_viz_component/frontend/build/static/js/main.af195e39.chunk.js.map
st_kedro_viz_component/frontend/build/static/js/runtime-main.44d30fc2.js
st_kedro_viz_component/frontend/build/static/js/runtime-main.44d30fc2.js.map
st_kedro_viz_component-0.0.1.dist-info/LICENSE
st_kedro_viz_component-0.0.1.dist-info/METADATA
st_kedro_viz_component-0.0.1.dist-info/WHEEL
st_kedro_viz_component-0.0.1.dist-info/top_level.txt
st_kedro_viz_component-0.0.1.dist-info/RECORD
